sysls/__init__.py
sysls/__main__.py
sysls-2.dist-info/LICENSE
sysls-2.dist-info/METADATA
sysls-2.dist-info/WHEEL
sysls-2.dist-info/entry_points.txt
sysls-2.dist-info/top_level.txt
sysls-2.dist-info/RECORD
